Metadata-Version: 2.1
Name: computer-vision-python
Version: 2.4.0
Summary: IT IS A VERY GOOD LIBRARY FOR COMPUTER VISION AND WHEN YOURE ARE MAKING THE PROJECT TRING
Home-page: https://github.com/Tring10/COMPUTERVISION/blob/main/mycv.zip
Author: OM NIRMALKAR
Author-email: info.craftfox@gmail.com
License: MIT
Download-URL: https://github.com/Tring10/COMPUTERVISION/blob/main/mycv.zip
Keywords: cv2,cv,tring,computer vision
Platform: UNKNOWN
Classifier: Development Status :: 4 - Beta
Classifier: Intended Audience :: Developers
Classifier: Topic :: Software Development :: Build Tools
Classifier: License :: OSI Approved :: MIT License
Classifier: Programming Language :: Python :: 3
Classifier: Programming Language :: Python :: 3.7
Classifier: Programming Language :: Python :: 3.9
Classifier: Programming Language :: Python :: 3.10
Classifier: Programming Language :: Python :: 3.11
License-File: LICENSE.txt
